dn/__init__.py
dn/src.py
dn/to.py
dn/util.py
dn-0.0.8.dist-info/LICENSE
dn-0.0.8.dist-info/METADATA
dn-0.0.8.dist-info/WHEEL
dn-0.0.8.dist-info/top_level.txt
dn-0.0.8.dist-info/RECORD
