Metadata-Version: 2.1
Name: dn
Version: 0.0.8
Summary: Tools for markdown parsing and generation
Author: Thor Whalen
License: mit
License-File: LICENSE
Requires-Dist: dol
Provides-Extra: all
Requires-Dist: pypdf; extra == "all"
Requires-Dist: mammoth; extra == "all"
Requires-Dist: pandas; extra == "all"
Requires-Dist: openpyxl; extra == "all"
Requires-Dist: tabulate; extra == "all"
Requires-Dist: python-pptx; extra == "all"
Requires-Dist: html2text; extra == "all"
Requires-Dist: nbconvert; extra == "all"
Requires-Dist: nbformat; extra == "all"
Provides-Extra: excel
Requires-Dist: pandas; extra == "excel"
Requires-Dist: openpyxl; extra == "excel"
Requires-Dist: tabulate; extra == "excel"
Provides-Extra: html
Requires-Dist: html2text; extra == "html"
Provides-Extra: notebook
Requires-Dist: nbconvert; extra == "notebook"
Requires-Dist: nbformat; extra == "notebook"
Provides-Extra: pdf
Requires-Dist: pypdf; extra == "pdf"
Provides-Extra: powerpoint
Requires-Dist: python-pptx; extra == "powerpoint"
Provides-Extra: word
Requires-Dist: mammoth; extra == "word"
